LICENSE
MANIFEST.in
README.rst
setup.py
MeshSync.egg-info/PKG-INFO
MeshSync.egg-info/SOURCES.txt
MeshSync.egg-info/dependency_links.txt
MeshSync.egg-info/entry_points.txt
MeshSync.egg-info/requires.txt
MeshSync.egg-info/top_level.txt
meshsync/__init__.py
meshsync/__main__.py
meshsync/mesh_sync.py
meshsync/vault.py