Metadata-Version: 2.1
Name: MeshSync
Version: 1.1.5
Summary: Command line tool to download/update Mesh projects with ease!
Home-page: https://rawa.dev
Author: Rawa Dev
Author-email: rawa@rawa.dev
License: UNKNOWN
Platform: UNKNOWN
License-File: LICENSE
